recolor_dots/__init__.py
recolor_dots/main.py
recolor_dots-0.1.3.dist-info/DESCRIPTION.rst
recolor_dots-0.1.3.dist-info/METADATA
recolor_dots-0.1.3.dist-info/RECORD
recolor_dots-0.1.3.dist-info/WHEEL
recolor_dots-0.1.3.dist-info/entry_points.txt
recolor_dots-0.1.3.dist-info/metadata.json
recolor_dots-0.1.3.dist-info/top_level.txt
