Metadata-Version: 2.0
Name: recolor-dots
Version: 0.1.3
Summary: Templates for dotfile recoloring
Home-page: http://github.com/raghavsub/recolor-dots
Author: Raghav Subramaniam
Author-email: raghavs511@gmail.com
License: MIT
Platform: UNKNOWN
Requires-Dist: docopt
Requires-Dist: pystache
Requires-Dist: pyyaml
